{"otherData": {},"traceEvents":[{"cat":"function","dur":40,"name":"void __cdecl Hare::Renderer2D::ShutDown(void)","ph":"X","pid":0,"tid":2668700135,"ts":784616875982},{"cat":"function","dur":64,"name":"__cdecl Hare::Application::~Application(void)","ph":"X","pid":0,"tid":2668700135,"ts":784616875981},{"cat":"function","dur":2,"name":"__cdecl Hare::OpenGLTexture2D::~OpenGLTexture2D(void)","ph":"X","pid":0,"tid":2668700135,"ts":784616876062},{"cat":"function","dur":23648,"name":"void __cdecl Hare::WindowsWindow::ShutDown(void)","ph":"X","pid":0,"tid":2668700135,"ts":784616876078},{"cat":"function","dur":23693,"name":"__cdecl Hare::WindowsWindow::~WindowsWindow(void)","ph":"X","pid":0,"tid":2668700135,"ts":784616876078}]}